mcp_coded_tools/__init__.py
mcp_coded_tools/cli.py
mcp_coded_tools/generator.py
mcp_coded_tools/schema_parser.py
mcp_coded_tools/templates.py
mcp_coded_tools-0.1.0.dist-info/licenses/LICENSE
mcp_coded_tools-0.1.0.dist-info/METADATA
mcp_coded_tools-0.1.0.dist-info/WHEEL
mcp_coded_tools-0.1.0.dist-info/entry_points.txt
mcp_coded_tools-0.1.0.dist-info/top_level.txt
mcp_coded_tools-0.1.0.dist-info/RECORD
