Metadata-Version: 2.4
Name: mcp-coded-tools
Version: 0.1.0
Summary: Generate discoverable code from MCP servers for agent tool usage
Author-email: Michael Ogundare <hey@michael.ng>
License-Expression: MIT
Project-URL: Homepage, https://github.com/bluman1/mcp-coded-tools
Project-URL: Repository, https://github.com/bluman1/mcp-coded-tools
Project-URL: Issues, https://github.com/bluman1/mcp-coded-tools/issues
Keywords: mcp,model-context-protocol,code-generation,ai-agents,codegen
Classifier: Development Status :: 3 - Alpha
Classifier: Intended Audience :: Developers
Classifier: Programming Language :: Python :: 3
Classifier: Programming Language :: Python :: 3.10
Classifier: Programming Language :: Python :: 3.11
Classifier: Programming Language :: Python :: 3.12
Classifier: Programming Language :: Python :: 3.13
Classifier: Programming Language :: Python :: 3.14
Requires-Python: >=3.10
License-File: LICENSE
Requires-Dist: mcp<2.0.0,>=1.2.0
Requires-Dist: inflection>=0.5.1
Requires-Dist: click>=8.3.0
Requires-Dist: jinja2>=3.1.6
Requires-Dist: watchdog>=4.0.0
Provides-Extra: dev
Requires-Dist: pytest>=8.4.0; extra == "dev"
Requires-Dist: pytest-asyncio>=0.24.0; extra == "dev"
Requires-Dist: pytest-cov>=5.0.0; extra == "dev"
Requires-Dist: black>=25.1.0; extra == "dev"
Requires-Dist: ruff>=0.14.0; extra == "dev"
Requires-Dist: mypy>=1.11.0; extra == "dev"
Dynamic: license-file
